sms_toolkit/__init__.py
sms_toolkit/constants/__init__.py
sms_toolkit/constants/encoding.py
sms_toolkit/constants/unicode_to_gsm_map.py
sms_toolkit/messages/__init__.py
sms_toolkit/messages/normalization.py
sms_toolkit/messages/profiling.py
sms_toolkit/utils/__init__.py
sms_toolkit/utils/encoding.py
sms_toolkit/utils/general.py
sms_toolkit/vobject/__init__.py
sms_toolkit/vobject/base.py
sms_toolkit/vobject/behavior.py
sms_toolkit/vobject/vcard.py
sms_toolkit-1.0.8.dist-info/LICENSE-2.0.txt
sms_toolkit-1.0.8.dist-info/METADATA
sms_toolkit-1.0.8.dist-info/WHEEL
sms_toolkit-1.0.8.dist-info/top_level.txt
sms_toolkit-1.0.8.dist-info/RECORD
