Metadata-Version: 2.1
Name: sms-toolkit
Version: 1.0.8
Summary: A collection of tools to work with SMS messages.
Home-page: https://github.com/chrisconlon-klaviyo/sms-toolkit
Author: Klaviyo
Author-email: community@klaviyo.com
License: MIT
Platform: UNKNOWN
Classifier: Programming Language :: Python :: 2.7
Classifier: Programming Language :: Python :: 3
Classifier: Programming Language :: Python :: 3.5
Classifier: Programming Language :: Python :: 3.6
Classifier: Programming Language :: Python :: 3.7
Classifier: Programming Language :: Python :: 3.8
Classifier: Operating System :: OS Independent
Classifier: Topic :: Software Development :: Libraries :: Python Modules
Requires-Python: >=2.7, !=3.0.*, !=3.1.*, !=3.2.*, !=3.3.*, !=3.4.*, <4
License-File: LICENSE-2.0.txt
